{"properties":{"connectionReferences":{"shared_commondataservice_1":{"runtimeSource":"embedded","connection":{},"api":{"name":"shared_commondataservice"}},"shared_commondataserviceforapps":{"runtimeSource":"embedded","connection":{},"api":{"name":"shared_commondataserviceforapps"}}},"definition":{"$schema":"https://schema.management.azure.com/providers/Microsoft.Logic/schemas/2016-06-01/workflowdefinition.json#","contentVersion":"1.0.0.0","parameters":{"$connections":{"defaultValue":{},"type":"Object"},"$authentication":{"defaultValue":{},"type":"SecureObject"}},"triggers":{"When_Account_BPF_is_Updated":{"type":"OpenApiConnectionWebhook","inputs":{"host":{"connectionName":"shared_commondataserviceforapps","operationId":"SubscribeWebhookTrigger","apiId":"/providers/Microsoft.PowerApps/apis/shared_commondataserviceforapps"},"parameters":{"subscriptionRequest/message":4,"subscriptionRequest/entityname":"leidos_bpfaccountprocess","subscriptionRequest/scope":4},"authentication":"@parameters('$authentication')"}}},"actions":{"Stage_value":{"runAfter":{},"type":"Compose","inputs":"@triggerOutputs()?['body/_activestageid_value']"},"BPF_Status_Reason":{"runAfter":{"Stage_value":["Succeeded"]},"type":"Compose","inputs":"@triggerOutputs()?['body/statuscode']"},"Account_Record":{"runAfter":{"BPF_Status_Reason":["Succeeded"]},"type":"OpenApiConnection","inputs":{"host":{"connectionName":"shared_commondataservice_1","operationId":"GetItem_V2","apiId":"/providers/Microsoft.PowerApps/apis/shared_commondataservice"},"parameters":{"dataset":"default.cds","table":"accounts","id":"@triggerOutputs()?['body/_bpf_accountid_value']"},"authentication":"@parameters('$authentication')"}},"Switch":{"runAfter":{"Account_Record":["Succeeded"]},"cases":{"Basic_Details":{"case":"c40b1ea2-8dc9-4711-a2ef-280b4a89ea23","actions":{"Update_a_record":{"runAfter":{},"type":"OpenApiConnection","inputs":{"host":{"connectionName":"shared_commondataserviceforapps","operationId":"UpdateRecord","apiId":"/providers/Microsoft.PowerApps/apis/shared_commondataserviceforapps"},"parameters":{"entityName":"accounts","recordId":"@outputs('Account_Record')?['body/accountid']","item/statuscode":1},"authentication":"@parameters('$authentication')"}}}},"Segmentation":{"case":"8f6f8aec-a442-48f0-8d94-f7ddcea4f4dd","actions":{"Condition":{"actions":{},"runAfter":{},"expression":{"equals":["@outputs('BPF_Status_Reason')",2]},"type":"If"}}},"Proposed_for_AMR":{"case":"92b356d1-878a-44c3-878c-381bd0733930","actions":{"Update_Account_to_Proposed_for_AMR":{"runAfter":{},"type":"OpenApiConnection","inputs":{"host":{"connectionName":"shared_commondataservice_1","operationId":"PatchItem_V2","apiId":"/providers/Microsoft.PowerApps/apis/shared_commondataservice"},"parameters":{"dataset":"default.cds","table":"accounts","id":"@outputs('Account_Record')?['body/accountid']","item/statuscode":445260000,"item/statecode":0,"item/_ownerid_type":""},"authentication":"@parameters('$authentication')"}}}}},"default":{"actions":{}},"expression":"@outputs('Stage_value')","type":"Switch"}},"outputs":{}}},"schemaVersion":"1.0.0.0"}