<?xml version="1.0" encoding="utf-8"?>
<WebResource xmlns:xsi="http://www.w3.org/2001/XMLSchema-instance">
  <WebResourceId>{04abd749-2248-ea11-a812-000d3a0bad17}</WebResourceId>
  <Name>north52_/formula/leidos_businessreviewanswers/1ot/f.04abd7492248ea11a812000d3a0bad17</Name>
  <DisplayName>8def2381-1ab2-467a-a7df-9d9dd4a6b9d4</DisplayName>
  <Description>North52Formula: Business Review Answers - Save - Perform Action -Update Summary on update of Answer</Description>
  <WebResourceType>4</WebResourceType>
  <IntroducedVersion>1.0</IntroducedVersion>
  <IsEnabledForMobileClient>0</IsEnabledForMobileClient>
  <IsAvailableForMobileOffline>0</IsAvailableForMobileOffline>
  <IsCustomizable>1</IsCustomizable>
  <CanBeDeleted>1</CanBeDeleted>
  <IsHidden>0</IsHidden>
  <FileName>/WebResources/north52_formulaleidos_businessreviewanswers1otf04a04ABD749-2248-EA11-A812-000D3A0BAD17</FileName>
</WebResource>